examples/cli.py
pylibbitcoin/__init__.py
pylibbitcoin/client.py
pylibbitcoin/error_code.py
pylibbitcoin-0.1.0.dist-info/METADATA
pylibbitcoin-0.1.0.dist-info/RECORD
pylibbitcoin-0.1.0.dist-info/WHEEL
pylibbitcoin-0.1.0.dist-info/top_level.txt
