Metadata-Version: 2.1
Name: pylibbitcoin
Version: 0.1.0
Summary: Python bindings for libbitcoin-server ZMQ interface
Home-page: https://github.com/libbitcoin/pylibbitcoin
Author: libbitcoin
Author-email: harmaarts@gmail.com
License: UNKNOWN
Project-URL: Bug Reports, https://github.com/libbitcoin/pylibbitcoin/issues
Project-URL: Source, https://github.com/libbitcoin/pylibbitcoin/
Keywords: bitcoin libbitcoin blockchain library zmq
Platform: UNKNOWN
Classifier: Development Status :: 3 - Alpha
Classifier: Intended Audience :: Developers
Classifier: Topic :: Software Development :: Libraries
Classifier: License :: OSI Approved :: MIT License
Classifier: Programming Language :: Python :: 3.6
Provides-Extra: test
Provides-Extra: dev
Requires-Dist: pyzmq
Requires-Dist: python-bitcoinlib
Requires-Dist: anytree
Provides-Extra: dev
Requires-Dist: flake8; extra == 'dev'
Provides-Extra: test
Requires-Dist: asynctest; extra == 'test'
